HISTORY
LICENSE
MANIFEST.in
README
setup.py
example/example1.py
gyagp/__init__.py
gyagp/module.py
gyagp.egg-info/PKG-INFO
gyagp.egg-info/SOURCES.txt
gyagp.egg-info/dependency_links.txt
gyagp.egg-info/requires.txt
gyagp.egg-info/top_level.txt
test/test_gyagp.py