Metadata-Version: 1.0
Name: gyagp
Version: 0.1.1
Summary: A small but full featured python project
Home-page: http://www.gyagp.com
Author: Yang Gu
Author-email: gyagp0@gmail.com
License: License :: OSI Approved :: BSD License
Download-URL: http://www.gyagp.com/gyagp-0.1.1.tar.gz
Keywords: gyagp
Platform: Platform Independent
Classifier: Development Status :: 5 - Production/Stable
Classifier: Environment :: Console
Classifier: Natural Language :: English
Classifier: Operating System :: OS Independent
Classifier: Programming Language :: Python :: 2
Classifier: Topic :: Utilities
Classifier: Topic :: Software Development :: Libraries
Classifier: Topic :: Software Development :: Libraries :: Python Modules
Classifier: Intended Audience :: Developers
Classifier: License :: OSI Approved :: BSD License
